sort_by_average/__init__.py
sort_by_average/call_func.py
sort_by_average/sort_by_average.py
sorting_by_average-0.1.0.dist-info/licenses/LICENSE
sorting_by_average-0.1.0.dist-info/METADATA
sorting_by_average-0.1.0.dist-info/WHEEL
sorting_by_average-0.1.0.dist-info/top_level.txt
sorting_by_average-0.1.0.dist-info/RECORD
