Metadata-Version: 2.4
Name: sorting-by-average
Version: 0.1.0
Summary: Python library for sorting collections of integers, dictionaries, or tuples based on their average values.
Author-email: Bartosz Biesiadecki <bbiesiadecki@protonmail.com>
License: MIT
Project-URL: Homepage, https://gitlab.com/biesiad99/sortingbyaverage
Requires-Python: >=3.6
License-File: LICENSE
Requires-Dist: numpy>=1.20
Provides-Extra: dev
Requires-Dist: pytest; extra == "dev"
Dynamic: license-file
